LICENSE
MANIFEST.in
README.md
detect_rpi.py
setup.py
include/smi_leds.h
python/libsmi_leds.c
python/libsmi_leds.h
python/module.c
smi_leds/rpi_dma_utils.c
smi_leds/rpi_dma_utils.h
smi_leds/rpi_pixleds_lib.c
smi_leds/rpi_smi_defs.h
smileds.egg-info/PKG-INFO
smileds.egg-info/SOURCES.txt
smileds.egg-info/dependency_links.txt
smileds.egg-info/requires.txt
smileds.egg-info/top_level.txt